NAVIAI_Jetson/NAVIAI_Jetson.cpython-36m-aarch64-linux-gnu.so
NAVIAI_Jetson/__init__.py
escaper_temp/__init__.py
escaper_utilities/__init__.py
escaper_utils/__init__.py
NAVIAI_Jetson-1.0.1.dist-info/METADATA
NAVIAI_Jetson-1.0.1.dist-info/WHEEL
NAVIAI_Jetson-1.0.1.dist-info/top_level.txt
NAVIAI_Jetson-1.0.1.dist-info/RECORD
